example/__init__.py
example/admin.py
example/apps.py
example/forms.py
example/models.py
example/tests.py
example/urls.py
example/views.py
example/migrations/__init__.py
project/__init__.py
project/asgi.py
project/settings.py
project/urls.py
project/wsgi.py
swift_crud/__init__.py
swift_crud/mixins.py
swift_crud/utils.py
swift_crud/views.py
tests/__init__.py
tests/test_views.py
django_swift_crud-0.1.2.dist-info/LICENSE
django_swift_crud-0.1.2.dist-info/METADATA
django_swift_crud-0.1.2.dist-info/WHEEL
django_swift_crud-0.1.2.dist-info/top_level.txt
django_swift_crud-0.1.2.dist-info/RECORD
